encodermap/__init__.py
encodermap/angle_dihedral_cartesian_encodermap.py
encodermap/autoencoder.py
encodermap/backmapping.py
encodermap/dihedral_backmapping.py
encodermap/encodermap.py
encodermap/misc.py
encodermap/moldata.py
encodermap/parameters.py
encodermap/plot.py
encodermap-2.0.1.dist-info/LICENSE
encodermap-2.0.1.dist-info/METADATA
encodermap-2.0.1.dist-info/WHEEL
encodermap-2.0.1.dist-info/top_level.txt
encodermap-2.0.1.dist-info/RECORD
