Metadata-Version: 2.1
Name: encodermap
Version: 2.0.1
Summary: python library for dimensionality reduction
Home-page: https://github.com/AG-Peter/encodermap
Author: Tobias Lemke
License: UNKNOWN
Platform: UNKNOWN
Classifier: Programming Language :: Python :: 3
Classifier: License :: OSI Approved :: GNU General Public License v3 (GPLv3)
Classifier: Operating System :: OS Independent
Requires-Dist: numpy
Requires-Dist: matplotlib
Requires-Dist: scipy
Requires-Dist: MDAnalysis
Requires-Dist: tqdm
